openconfig/__init__.py
openconfig-0.0.1.dist-info/DESCRIPTION.rst
openconfig-0.0.1.dist-info/METADATA
openconfig-0.0.1.dist-info/RECORD
openconfig-0.0.1.dist-info/WHEEL
openconfig-0.0.1.dist-info/metadata.json
openconfig-0.0.1.dist-info/top_level.txt
