Metadata-Version: 2.0
Name: openconfig
Version: 0.0.1
Summary: Vendor-neutral, model-driven network management designed by users
Home-page: https://github.com/mirceaulinic/python-openconfig
Author: Mircea Ulinic
Author-email: mircea.ulinic@gmail.com
License: Apache License 2.0
Keywords: openconfig,networking,yang,vendor-neutral
Platform: UNKNOWN
Classifier: Development Status :: 5 - Production/Stable
Classifier: Topic :: Utilities
Classifier: Topic :: System :: Networking
Classifier: Programming Language :: Python
Classifier: Programming Language :: Python :: 2
Classifier: Programming Language :: Python :: 2.7
Classifier: Programming Language :: Python :: 3
Classifier: Programming Language :: Python :: 3.4
Classifier: Programming Language :: Python :: 3.5
Classifier: Programming Language :: Python :: 3.6
Classifier: Operating System :: POSIX :: Linux
Classifier: Operating System :: POSIX :: Linux
Classifier: Operating System :: MacOS
Classifier: Intended Audience :: Developers
Requires-Dist: napalm (>=2.0.0)
